devhub_cms_mcp/__init__.py
devhub_cms_mcp/server.py
devhub_cms_mcp_fastmcp-0.3.1.dist-info/METADATA
devhub_cms_mcp_fastmcp-0.3.1.dist-info/WHEEL
devhub_cms_mcp_fastmcp-0.3.1.dist-info/entry_points.txt
devhub_cms_mcp_fastmcp-0.3.1.dist-info/top_level.txt
devhub_cms_mcp_fastmcp-0.3.1.dist-info/RECORD
